telepointer/__init__.py
telepointer/main.py
telepointer/landmarking/landmarker.py
telepointer/landmarking/landmarker_processing.py
telepointer/landmarking/post_processing.py
telepointer/mouse_control/mouse_controller.py
telepointer/mouse_control/mouse_driver.py
telepointer/third_party/landmarking/landmarker.py
telepointer/video/video_source.py
telepointer-0.0.5.dist-info/licenses/LICENSE
tpctrl/__init__.py
tpctrl/main.py
telepointer-0.0.5.dist-info/METADATA
telepointer-0.0.5.dist-info/WHEEL
telepointer-0.0.5.dist-info/entry_points.txt
telepointer-0.0.5.dist-info/top_level.txt
telepointer-0.0.5.dist-info/RECORD
