Metadata-Version: 2.4
Name: telepointer
Version: 0.0.5
Summary: Face-tracking cursor controller
Requires-Python: >=3.12
License-File: LICENSE
Requires-Dist: click>=8.2.1
Requires-Dist: mediapipe>=0.10.31
Requires-Dist: mss>=10.0.0
Requires-Dist: numpy>=1.26.4
Requires-Dist: opencv-python>=4.11.0.86
Requires-Dist: pynput>=1.8.1
Requires-Dist: scipy>=1.16.0
Dynamic: license-file
